WRaThioN/WRaThioN.py
WRaThioN/__init__.py
WRaThioN-0.1.1.dist-info/LICENSE.md
WRaThioN-0.1.1.dist-info/METADATA
WRaThioN-0.1.1.dist-info/WHEEL
WRaThioN-0.1.1.dist-info/top_level.txt
WRaThioN-0.1.1.dist-info/RECORD
