Metadata-Version: 2.1
Name: WRaThioN
Version: 0.1.1
Summary: WRaThioN: WRTN Client For Python
Home-page: https://github.com/KimEJ/WRaThioN
Author: kimuj5090
Author-email: kimuj5090@gmail.com
License: MIT
Keywords: WRTN,WRaThioN
Classifier: Programming Language :: Python :: 3
Classifier: Programming Language :: Python :: 3.2
Classifier: Programming Language :: Python :: 3.3
Classifier: Programming Language :: Python :: 3.4
Classifier: Programming Language :: Python :: 3.5
Classifier: Programming Language :: Python :: 3.6
Classifier: Programming Language :: Python :: 3.7
Classifier: Programming Language :: Python :: 3.9
Classifier: Programming Language :: Python :: 3.10
Classifier: Programming Language :: Python :: 3.11
Classifier: License :: OSI Approved :: MIT License
Requires-Python: >=3
License-File: LICENSE.md
Requires-Dist: pyjwt
Requires-Dist: sseclient-py
Requires-Dist: requests
Requires-Dist: argparse
